ncal/__init__.py
ncal/__main__.py
ncal/cli.py
ncal/config.py
ncal/core.py
ncal/gcal_setup.py
ncal/notion_utils.py
ncal/py.typed
ncal-0.3.0.dist-info/entry_points.txt
ncal-0.3.0.dist-info/LICENSE
ncal-0.3.0.dist-info/WHEEL
ncal-0.3.0.dist-info/METADATA
ncal-0.3.0.dist-info/RECORD
