Metadata-Version: 2.1
Name: ncal
Version: 0.3.0
Summary: 
Home-page: https://sg60.github.io/ncal/
License: GNU GPL
Author: Sam Greening
Author-email: samjg60@gmail.com
Requires-Python: >=3.9,<4.0
Classifier: License :: Other/Proprietary License
Classifier: Programming Language :: Python :: 3
Classifier: Programming Language :: Python :: 3.10
Classifier: Programming Language :: Python :: 3.9
Requires-Dist: arrow (>=1.2.1,<2.0.0)
Requires-Dist: google-api-python-client (>=2.36.0,<3.0.0)
Requires-Dist: google-auth-oauthlib (>=0.4.6,<0.6.0)
Requires-Dist: notion-client (>=0.9.0,<0.10.0)
Requires-Dist: pydantic (>=1.9.0,<2.0.0)
Requires-Dist: python-dateutil (>=2.8.2,<3.0.0)
Requires-Dist: python-dotenv (>=0.19.2,<0.21.0)
Requires-Dist: tomli (>=2.0.0,<3.0.0)
Requires-Dist: typer (>=0.4.0,<0.5.0)
Project-URL: Repository, https://github.com/SG60/Notion-and-Google-Calendar-2-Way-Sync
